zc.catalog-3.0-py2.7-nspkg.pth
zc/catalog/__init__.py
zc/catalog/callablewrapper.rst
zc/catalog/catalogindex.py
zc/catalog/configure.zcml
zc/catalog/extentcatalog.py
zc/catalog/extentcatalog.rst
zc/catalog/globber.py
zc/catalog/globber.rst
zc/catalog/i18n.py
zc/catalog/index.py
zc/catalog/interfaces.py
zc/catalog/legacy.rst
zc/catalog/normalizedindex.rst
zc/catalog/setindex.rst
zc/catalog/stemmer.py
zc/catalog/stemmer.rst
zc/catalog/tests.py
zc/catalog/valueindex.rst
zc/catalog/browser/README.rst
zc/catalog/browser/__init__.py
zc/catalog/browser/configure.zcml
zc/catalog/browser/ftesting.zcml
zc/catalog/browser/tests.py
zc.catalog-3.0.dist-info/DESCRIPTION.rst
zc.catalog-3.0.dist-info/METADATA
zc.catalog-3.0.dist-info/RECORD
zc.catalog-3.0.dist-info/WHEEL
zc.catalog-3.0.dist-info/metadata.json
zc.catalog-3.0.dist-info/namespace_packages.txt
zc.catalog-3.0.dist-info/top_level.txt
